<?xml version="1.0" encoding="UTF-8"?>
<PurchaseOrder>
  <Header>
    <OrderId>PO-DEMO-001</OrderId>
    <BuyerId>BUYER-001</BuyerId>
    <SupplierId>SUPP-001</SupplierId>
    <OrderDate>2026-04-28</OrderDate>
    <PaymentTerms>NET30</PaymentTerms>
    <Currency>USD</Currency>
  </Header>
  <DeliveryAddress>
    <Street>123 Commerce Avenue</Street>
    <City>New York</City>
    <PostalCode>10001</PostalCode>
    <Country>USA</Country>
  </DeliveryAddress>
  <LineItems>
    <LineItem>
      <LineNumber>1</LineNumber>
      <ProductCode>WIDGET-A</ProductCode>
      <Description>Premium Widget Type A</Description>
      <Quantity>100</Quantity>
      <UnitPrice>25.00</UnitPrice>
      <LineTotal>2500.00</LineTotal>
    </LineItem>
    <LineItem>
      <LineNumber>2</LineNumber>
      <ProductCode>GADGET-B</ProductCode>
      <Description>Electronic Gadget Type B</Description>
      <Quantity>50</Quantity>
      <UnitPrice>80.00</UnitPrice>
      <LineTotal>4000.00</LineTotal>
    </LineItem>
  </LineItems>
  <OrderTotal>6500.00</OrderTotal>
</PurchaseOrder>
